bw_timex/__init__.py
bw_timex/dynamic_biosphere_builder.py
bw_timex/edge_extractor.py
bw_timex/helper_classes.py
bw_timex/matrix_modifier.py
bw_timex/timeline_builder.py
bw_timex/timex_lca.py
bw_timex/utils.py
bw_timex/data/decay_multipliers.json
bw_timex-0.3.4.dist-info/licenses/LICENSE
bw_timex-0.3.4.dist-info/METADATA
bw_timex-0.3.4.dist-info/WHEEL
bw_timex-0.3.4.dist-info/top_level.txt
bw_timex-0.3.4.dist-info/RECORD
