Metadata-Version: 2.4
Name: bw_timex
Version: 0.3.4
Summary: Time-explicit Life Cycle Assessment
Author-email: Timo Diepers <timo.diepers@ltt.rwth-aachen.de>, Amelie Müller <a.muller@cml.leidenuniv.nl>, Arthur Jakobs <artos.jakobs@psi.ch>
Maintainer-email: Timo Diepers <timo.diepers@ltt.rwth-aachen.de>, Amelie Müller <a.muller@cml.leidenuniv.nl>, Arthur Jakobs <artos.jakobs@psi.ch>
Project-URL: source, https://github.com/brightway-lca/bw_timex
Project-URL: homepage, https://github.com/brightway-lca/bw_timex
Project-URL: tracker, https://github.com/brightway-lca/bw_timex/issues
Keywords: brightway,Life Cycle Assessment,LCA,time-explicit,dynamic,prospective
Classifier: Development Status :: 3 - Alpha
Classifier: Intended Audience :: Science/Research
Classifier: License :: OSI Approved :: BSD License
Classifier: Natural Language :: English
Classifier: Programming Language :: Python :: 3
Classifier: Operating System :: OS Independent
Classifier: Topic :: Scientific/Engineering
Requires-Python: >=3.11
License-File: LICENSE
Requires-Dist: bw2calc==2.3
Requires-Dist: bw2data==4.5.4
Requires-Dist: bw_graph_tools>0.4
Requires-Dist: numpy
Requires-Dist: pandas
Requires-Dist: tqdm
Requires-Dist: bw_temporalis>=1.1
Requires-Dist: dynamic_characterization>=1.2.0
Requires-Dist: matplotlib
Requires-Dist: seaborn
Requires-Dist: loguru
Requires-Dist: ipython
Requires-Dist: ipywidgets
Provides-Extra: testing
Requires-Dist: setuptools; extra == "testing"
Requires-Dist: pytest; extra == "testing"
Requires-Dist: pytest-cov; extra == "testing"
Provides-Extra: dev
Requires-Dist: pre-commit; extra == "dev"
Requires-Dist: pylint; extra == "dev"
Provides-Extra: docs
Requires-Dist: ipython; extra == "docs"
Requires-Dist: pydata-sphinx-theme; extra == "docs"
Requires-Dist: myst-parser; extra == "docs"
Requires-Dist: sphinx-click; extra == "docs"
Requires-Dist: sphinx-design; extra == "docs"
Requires-Dist: sphinx-notfound-page; extra == "docs"
Requires-Dist: sphinx-favicon; extra == "docs"
Requires-Dist: sphinx-copybutton; extra == "docs"
Requires-Dist: sphinx-autobuild; extra == "docs"
Dynamic: license-file
